{
   "data": [{
      "name": "初始访问",
      "items": [{
         "id": "TA0001_T1189",
         "name": "路过式攻击",
         "important": false
      }, {
         "id": "TA0001_T1190",
         "name": "面向公众应用的利用",
         "important": false
      }, {
         "id": "TA0001_T1133",
         "name": "外部远程服务",
         "important": false
      }, {
         "id": "TA0001_T1200",
         "name": "硬件添加",
         "important": false
      }, {
         "id": "TA0001_T1091",
         "name": "通过移动存储进行复制",
         "important": false
      }, {
         "id": "TA0001_T1193",
         "name": "鱼叉式钓鱼攻击附件",
         "important": false
      }, {
         "id": "TA0001_T1192",
         "name": "鱼叉式钓鱼攻击链接",
         "important": false
      }, {
         "id": "TA0001_T1194",
         "name": "通过服务进行鱼叉式钓鱼攻击",
         "important": false
      }, {
         "id": "TA0001_T1195",
         "name": "供应链攻击",
         "important": false
      }, {
         "id": "TA0001_T1199",
         "name": "可信关系",
         "important": false
      }, {
         "id": "TA0001_T1078",
         "name": "有效账号",
         "important": false
      }]
   }, {
      "name": "执行",
      "items": [{
         "id": "TA0002_T1155",
         "name": "AppScript",
         "important": false
      }, {
         "id": "TA0002_T1191",
         "name": "CMSTP",
         "important": false
      }, {
         "id": "TA0002_T1059",
         "name": "命令行界面",
         "important": false
      }, {
         "id": "TA0002_T1223",
         "name": "HTML编译文件",
         "important": false
      }, {
         "id": "TA0002_T1175",
         "name": "COM和分布式COM",
         "important": false
      }, {
         "id": "TA0002_T1196",
         "name": "控制面板项目",
         "important": false
      }, {
         "id": "TA0002_T1173",
         "name": "动态数据交换",
         "important": false
      }, {
         "id": "TA0002_T1106",
         "name": "通过API接口执行",
         "important": false
      }, {
         "id": "TA0002_T1129",
         "name": "通过模块加载执行",
         "important": false
      }, {
         "id": "TA0002_T1203",
         "name": "客户端执行利用",
         "important": false
      }, {
         "id": "TA0002_T1061",
         "name": "图形用户界面",
         "important": false
      }, {
         "id": "TA0002_T1118",
         "name": "InstallUtil工具",
         "important": false
      }, {
         "id": "TA0002_T1152",
         "name": "Launchctl工具",
         "important": false
      }, {
         "id": "TA0002_T1168",
         "name": "本地作业调度",
         "important": false
      }, {
         "id": "TA0002_T1177",
         "name": "LSASS驱动程序",
         "important": false
      }, {
         "id": "TA0002_T1170",
         "name": "Mshta命令",
         "important": false
      }, {
         "id": "TA0002_T1086",
         "name": "PowerShell",
         "important": false
      }, {
         "id": "TA0002_T1121",
         "name": "Regsvcs/Regasm命令",
         "important": false
      }, {
         "id": "TA0002_T1117",
         "name": "Regsvr32命令",
         "important": false
      }, {
         "id": "TA0002_T1085",
         "name": "Rundll32命令",
         "important": false
      }, {
         "id": "TA0002_T1053",
         "name": "定时任务",
         "important": false
      }, {
         "id": "TA0002_T1064",
         "name": "脚本编程",
         "important": false
      }, {
         "id": "TA0002_T1035",
         "name": "服务执行",
         "important": false
      }, {
         "id": "TA0002_T1218",
         "name": "签名二进制代理执行",
         "important": false
      }, {
         "id": "TA0002_T1216",
         "name": "签名脚本代理执行",
         "important": false
      }, {
         "id": "TA0002_T1153",
         "name": "Source命令",
         "important": false
      }, {
         "id": "TA0002_T1151",
         "name": "文件名后加空格",
         "important": false
      }, {
         "id": "TA0002_T1072",
         "name": "第三方软件",
         "important": false
      }, {
         "id": "TA0002_T1154",
         "name": "Trap命令",
         "important": false
      }, {
         "id": "TA0002_T1127",
         "name": "可信的开发工具",
         "important": false
      }, {
         "id": "TA0002_T1204",
         "name": "用户执行",
         "important": false
      }, {
         "id": "TA0002_T1047",
         "name": "Windows管理指令集",
         "important": false
      }, {
         "id": "TA0002_T1028",
         "name": "Windows远程管理",
         "important": false
      }, {
         "id": "TA0002_T1220",
         "name": "XSL脚本处理",
         "important": false
      }]
   }, {
      "name": "持久化",
      "items": [{
         "id": "TA0003_T1156",
         "name": "bashrc",
         "important": false
      }, {
         "id": "TA0003_T1015",
         "name": "辅助功能",
         "important": false
      }, {
         "id": "TA0003_T1098",
         "name": "账号操纵",
         "important": false
      }, {
         "id": "TA0003_T1182",
         "name": "AppCert DLL",
         "important": false
      }, {
         "id": "TA0003_T1103",
         "name": "AppInit DLL",
         "important": false
      }, {
         "id": "TA0003_T1138",
         "name": "应用兼容转接",
         "important": false
      }, {
         "id": "TA0003_T1131",
         "name": "身份认证包",
         "important": false
      }, {
         "id": "TA0003_T1197",
         "name": "BITS作业",
         "important": false
      }, {
         "id": "TA0003_T1067",
         "name": "Bootkit",
         "important": false
      }, {
         "id": "TA0003_T1176",
         "name": "浏览器扩展",
         "important": false
      }, {
         "id": "TA0003_T1042",
         "name": "更改默认文件关联",
         "important": false
      }, {
         "id": "TA0003_T1109",
         "name": "组件固件",
         "important": false
      }, {
         "id": "TA0003_T1122",
         "name": "COM劫持",
         "important": false
      }, {
         "id": "TA0003_T1136",
         "name": "创建账号",
         "important": false
      }, {
         "id": "TA0003_T1038",
         "name": "DLL搜索顺序劫持",
         "important": false
      }, {
         "id": "TA0003_T1157",
         "name": "Dylib劫持",
         "important": false
      }, {
         "id": "TA0003_T1519",
         "name": "Emond",
         "important": false
      }, {
         "id": "TA0003_T1133",
         "name": "外部远程服务",
         "important": false
      }, {
         "id": "TA0003_T1044",
         "name": "文件系统权限缺陷",
         "important": false
      }, {
         "id": "TA0003_T1158",
         "name": "隐藏文件和目录",
         "important": false
      }, {
         "id": "TA0003_T1179",
         "name": "Hook",
         "important": false
      }, {
         "id": "TA0003_T1062",
         "name": "管理程序",
         "important": false
      }, {
         "id": "TA0003_T1183",
         "name": "图像文件执行选项注入",
         "important": false
      }, {
         "id": "TA0003_T1525",
         "name": "植入容器镜像",
         "important": false
      }, {
         "id": "TA0003_T1215",
         "name": "内核模块和扩展",
         "important": false
      }, {
         "id": "TA0003_T1159",
         "name": "启动代理",
         "important": false
      }, {
         "id": "TA0003_T1160",
         "name": "启动守护进程",
         "important": false
      }, {
         "id": "TA0003_T1152",
         "name": "Launchctl工具",
         "important": false
      }, {
         "id": "TA0003_T1161",
         "name": "LC_LOAD_DYLIB添加",
         "important": false
      }, {
         "id": "TA0003_T1168",
         "name": "本地作业调度",
         "important": false
      }, {
         "id": "TA0003_T1162",
         "name": "登录项",
         "important": false
      }, {
         "id": "TA0003_T1037",
         "name": "登录脚本",
         "important": false
      }, {
         "id": "TA0003_T1177",
         "name": "LSASS驱动程序",
         "important": false
      }, {
         "id": "TA0003_T1031",
         "name": "修改现有服务",
         "important": false
      }, {
         "id": "TA0003_T1128",
         "name": "Netsh Helper DLL",
         "important": false
      }, {
         "id": "TA0003_T1050",
         "name": "新建服务",
         "important": false
      }, {
         "id": "TA0003_T1137",
         "name": "Office应用启动",
         "important": false
      }, {
         "id": "TA0003_T1034",
         "name": "路径拦截",
         "important": false
      }, {
         "id": "TA0003_T1150",
         "name": "Plist修改",
         "important": false
      }, {
         "id": "TA0003_T1205",
         "name": "端口试探",
         "important": false
      }, {
         "id": "TA0003_T1013",
         "name": "端口监控",
         "important": false
      }, {
         "id": "TA0003_T1504",
         "name": "PowerShell配置文件",
         "important": false
      }, {
         "id": "TA0003_T1163",
         "name": "Rc.common",
         "important": false
      }, {
         "id": "TA0003_T1164",
         "name": "重新打开应用",
         "important": false
      }, {
         "id": "TA0003_T1108",
         "name": "冗余访问",
         "important": false
      }, {
         "id": "TA0003_T1060",
         "name": "注册表运行键/启动文件夹",
         "important": false
      }, {
         "id": "TA0003_T1053",
         "name": "定时任务",
         "important": false
      }, {
         "id": "TA0003_T1180",
         "name": "屏幕保护",
         "important": false
      }, {
         "id": "TA0003_T1101",
         "name": "安全支持提供者",
         "important": false
      }, {
         "id": "TA0003_T1505",
         "name": "服务器软件组件",
         "important": false
      }, {
         "id": "TA0003_T1058",
         "name": "服务注册权限缺陷",
         "important": false
      }, {
         "id": "TA0003_T1166",
         "name": "Setuid和Setgid",
         "important": false
      }, {
         "id": "TA0003_T1023",
         "name": "快捷方式修改",
         "important": false
      }, {
         "id": "TA0003_T1198",
         "name": "SIP和信任提供商劫持",
         "important": false
      }, {
         "id": "TA0003_T1165",
         "name": "启动项",
         "important": false
      }, {
         "id": "TA0003_T1019",
         "name": "系统固件",
         "important": false
      }, {
         "id": "TA0003_T1501",
         "name": "Systemd服务",
         "important": false
      }, {
         "id": "TA0003_T1209",
         "name": "时间服务器",
         "important": false
      }, {
         "id": "TA0003_T1154",
         "name": "Trap命令",
         "important": false
      }, {
         "id": "TA0003_T1078",
         "name": "有效账号",
         "important": false
      }, {
         "id": "TA0003_T1100",
         "name": "Web命令执行环境",
         "important": false
      }, {
         "id": "TA0003_T1084",
         "name": "WMI事件订阅",
         "important": false
      }, {
         "id": "TA0003_T1004",
         "name": "Winlogon Helper DLL",
         "important": false
      }]
   }, {
      "name": "权限升级",
      "items": [{
         "id": "TA0004_T1134",
         "name": "访问令牌操纵",
         "important": false
      }, {
         "id": "TA0004_T1015",
         "name": "辅助功能",
         "important": false
      }, {
         "id": "TA0004_T1182",
         "name": "AppCert DLL",
         "important": false
      }, {
         "id": "TA0004_T1103",
         "name": "AppInit DLL",
         "important": false
      }, {
         "id": "TA0004_T1138",
         "name": "应用兼容转接",
         "important": false
      }, {
         "id": "TA0004_T1088",
         "name": "UAC绕过",
         "important": false
      }, {
         "id": "TA0004_T1038",
         "name": "DLL搜索顺序劫持",
         "important": false
      }, {
         "id": "TA0004_T1157",
         "name": "Dylib劫持",
         "important": false
      }, {
         "id": "TA0004_T1514",
         "name": "以提示用户输入凭据的方式升级权限",
         "important": false
      }, {
         "id": "TA0004_T1519",
         "name": "Emond",
         "important": false
      }, {
         "id": "TA0004_T1068",
         "name": "提权利用",
         "important": false
      }, {
         "id": "TA0004_T1181",
         "name": "EWM注入",
         "important": false
      }, {
         "id": "TA0004_T1044",
         "name": "文件系统权限缺陷",
         "important": false
      }, {
         "id": "TA0004_T1179",
         "name": "Hook",
         "important": false
      }, {
         "id": "TA0004_T1183",
         "name": "图像文件执行选项注入",
         "important": false
      }, {
         "id": "TA0004_T1160",
         "name": "启动守护进程",
         "important": false
      }, {
         "id": "TA0004_T1050",
         "name": "新建服务",
         "important": false
      }, {
         "id": "TA0004_T1502",
         "name": "伪造父进程PID",
         "important": false
      }, {
         "id": "TA0004_T1034",
         "name": "路径拦截",
         "important": false
      }, {
         "id": "TA0004_T1150",
         "name": "Plist修改",
         "important": false
      }, {
         "id": "TA0004_T1013",
         "name": "端口监控",
         "important": false
      }, {
         "id": "TA0004_T1504",
         "name": "PowerShell配置文件",
         "important": false
      }, {
         "id": "TA0004_T1055",
         "name": "进程注入",
         "important": false
      }, {
         "id": "TA0004_T1053",
         "name": "定时任务",
         "important": false
      }, {
         "id": "TA0004_T1058",
         "name": "服务注册权限缺陷",
         "important": false
      }, {
         "id": "TA0004_T1166",
         "name": "Setuid和Setgid",
         "important": false
      }, {
         "id": "TA0004_T1178",
         "name": "SID-History 注入",
         "important": false
      }, {
         "id": "TA0004_T1165",
         "name": "启动项",
         "important": false
      }, {
         "id": "TA0004_T1169",
         "name": "Sudo命令",
         "important": false
      }, {
         "id": "TA0004_T1206",
         "name": "Sudo缓存",
         "important": false
      }, {
         "id": "TA0004_T1078",
         "name": "有效账号",
         "important": false
      }, {
         "id": "TA0004_T1100",
         "name": "Web命令执行环境",
         "important": false
      }]
   }, {
      "name": "防御逃逸",
      "items": [{
         "id": "TA0005_T1134",
         "name": "访问令牌操纵",
         "important": false
      }, {
         "id": "TA0005_T1527",
         "name": "应用程序访问令牌",
         "important": false
      }, {
         "id": "TA0005_T1009",
         "name": "二进制填充",
         "important": false
      }, {
         "id": "TA0005_T1197",
         "name": "BITS作业",
         "important": false
      }, {
         "id": "TA0005_T1088",
         "name": "UAC绕过",
         "important": false
      }, {
         "id": "TA0005_T1146",
         "name": "清除命令历史",
         "important": false
      }, {
         "id": "TA0005_T1191",
         "name": "CMSTP",
         "important": false
      }, {
         "id": "TA0005_T1116",
         "name": "代码签名",
         "important": false
      }, {
         "id": "TA0005_T1500",
         "name": "交付后编译",
         "important": false
      }, {
         "id": "TA0005_T1223",
         "name": "HTML编译文件",
         "important": false
      }, {
         "id": "TA0005_T1109",
         "name": "组件固件",
         "important": false
      }, {
         "id": "TA0005_T1122",
         "name": "COM劫持",
         "important": false
      }, {
         "id": "TA0005_T1090",
         "name": "连接代理",
         "important": false
      }, {
         "id": "TA0005_T1196",
         "name": "控制面板项目",
         "important": false
      }, {
         "id": "TA0005_T1207",
         "name": "DCShadow",
         "important": false
      }, {
         "id": "TA0005_T1140",
         "name": "文件或信息解混淆和解码",
         "important": false
      }, {
         "id": "TA0005_T1089",
         "name": "禁用安全工具",
         "important": false
      }, {
         "id": "TA0005_T1038",
         "name": "DLL搜索顺序劫持",
         "important": false
      }, {
         "id": "TA0005_T1073",
         "name": "DLL侧载",
         "important": false
      }, {
         "id": "TA0005_T1480",
         "name": "执行护栏",
         "important": false
      }, {
         "id": "TA0005_T1211",
         "name": "利用漏洞进行防御逃逸",
         "important": false
      }, {
         "id": "TA0005_T1181",
         "name": "EWM注入",
         "important": false
      }, {
         "id": "TA0005_T1222",
         "name": "文件权限修改",
         "important": false
      }, {
         "id": "TA0005_T1107",
         "name": "文件删除",
         "important": false
      }, {
         "id": "TA0005_T1006",
         "name": "文件系统逻辑偏移",
         "important": false
      }, {
         "id": "TA0005_T1144",
         "name": "关守绕过",
         "important": false
      }, {
         "id": "TA0005_T1484",
         "name": "组策略修改",
         "important": false
      }, {
         "id": "TA0005_T1158",
         "name": "隐藏文件和目录",
         "important": false
      }, {
         "id": "TA0005_T1147",
         "name": "隐藏用户",
         "important": false
      }, {
         "id": "TA0005_T1143",
         "name": "隐藏窗口",
         "important": false
      }, {
         "id": "TA0005_T1148",
         "name": "HISTCONTROL",
         "important": false
      }, {
         "id": "TA0005_T1183",
         "name": "图像文件执行选项注入",
         "important": false
      }, {
         "id": "TA0005_T1054",
         "name": "指示信号拦截",
         "important": false
      }, {
         "id": "TA0005_T1066",
         "name": "删除工具中指标",
         "important": false
      }, {
         "id": "TA0005_T1070",
         "name": "删除主机上指示信息",
         "important": false
      }, {
         "id": "TA0005_T1202",
         "name": "间接命令执行",
         "important": false
      }, {
         "id": "TA0005_T1130",
         "name": "安装根证书",
         "important": false
      }, {
         "id": "TA0005_T1118",
         "name": "InstallUtil工具",
         "important": false
      }, {
         "id": "TA0005_T1152",
         "name": "Launchctl工具",
         "important": false
      }, {
         "id": "TA0005_T1149",
         "name": "LC_MAIN劫持",
         "important": false
      }, {
         "id": "TA0005_T1036",
         "name": "伪装",
         "important": false
      }, {
         "id": "TA0005_T1112",
         "name": "注册表修改",
         "important": false
      }, {
         "id": "TA0005_T1170",
         "name": "Mshta命令",
         "important": false
      }, {
         "id": "TA0005_T1126",
         "name": "网络共享连接删除",
         "important": false
      }, {
         "id": "TA0005_T1096",
         "name": "NTFS文件属性",
         "important": false
      }, {
         "id": "TA0005_T1027",
         "name": "混淆文件或信息",
         "important": false
      }, {
         "id": "TA0005_T1502",
         "name": "伪造父进程PID",
         "important": false
      }, {
         "id": "TA0005_T1150",
         "name": "Plist修改",
         "important": false
      }, {
         "id": "TA0005_T1205",
         "name": "端口试探",
         "important": false
      }, {
         "id": "TA0005_T1186",
         "name": "进程Doppelgänging",
         "important": false
      }, {
         "id": "TA0005_T1093",
         "name": "进程替换",
         "important": false
      }, {
         "id": "TA0005_T1055",
         "name": "进程注入",
         "important": false
      }, {
         "id": "TA0005_T1108",
         "name": "冗余访问",
         "important": false
      }, {
         "id": "TA0005_T1121",
         "name": "Regsvcs/Regasm命令",
         "important": false
      }, {
         "id": "TA0005_T1117",
         "name": "Regsvr32命令",
         "important": false
      }, {
         "id": "TA0005_T1536",
         "name": "还原云实例",
         "important": false
      }, {
         "id": "TA0005_T1014",
         "name": "Rootkit",
         "important": false
      }, {
         "id": "TA0005_T1085",
         "name": "Rundll32命令",
         "important": false
      }, {
         "id": "TA0005_T1064",
         "name": "脚本编程",
         "important": false
      }, {
         "id": "TA0005_T1218",
         "name": "签名二进制代理执行",
         "important": false
      }, {
         "id": "TA0005_T1216",
         "name": "签名脚本代理执行",
         "important": false
      }, {
         "id": "TA0005_T1198",
         "name": "SIP和信任提供商劫持",
         "important": false
      }, {
         "id": "TA0005_T1045",
         "name": "软件加壳",
         "important": false
      }, {
         "id": "TA0005_T1151",
         "name": "文件名后加空格",
         "important": false
      }, {
         "id": "TA0005_T1221",
         "name": "模板注入",
         "important": false
      }, {
         "id": "TA0005_T1099",
         "name": "Timestomp工具",
         "important": false
      }, {
         "id": "TA0005_T1127",
         "name": "可信的开发工具",
         "important": false
      }, {
         "id": "TA0005_T1535",
         "name": "未使用/不支持的云区域",
         "important": false
      }, {
         "id": "TA0005_T1078",
         "name": "有效账号",
         "important": false
      }, {
         "id": "TA0005_T1497",
         "name": "虚拟化/沙箱逃逸",
         "important": false
      }, {
         "id": "TA0005_T1102",
         "name": "Web服务",
         "important": false
      }, {
         "id": "TA0005_T1506",
         "name": "Web会话Cookie",
         "important": false
      }, {
         "id": "TA0005_T1220",
         "name": "XSL脚本处理",
         "important": false
      }]
   }, {
      "name": "凭据访问",
      "items": [{
         "id": "TA0006_T1098",
         "name": "账号操纵",
         "important": false
      }, {
         "id": "TA0006_T1139",
         "name": "Bash历史",
         "important": false
      }, {
         "id": "TA0006_T1110",
         "name": "暴力破解",
         "important": false
      }, {
         "id": "TA0006_T1522",
         "name": "云实例元数据API",
         "important": false
      }, {
         "id": "TA0006_T1003",
         "name": "凭据转储",
         "important": false
      }, {
         "id": "TA0006_T1503",
         "name": "Web浏览器凭据",
         "important": false
      }, {
         "id": "TA0006_T1081",
         "name": "文件中的凭据",
         "important": false
      }, {
         "id": "TA0006_T1214",
         "name": "注册表中的凭据",
         "important": false
      }, {
         "id": "TA0006_T1212",
         "name": "凭据访问利用",
         "important": false
      }, {
         "id": "TA0006_T1187",
         "name": "强制认证",
         "important": false
      }, {
         "id": "TA0006_T1179",
         "name": "Hook",
         "important": false
      }, {
         "id": "TA0006_T1056",
         "name": "输入捕捉",
         "important": false
      }, {
         "id": "TA0006_T1141",
         "name": "输入提示",
         "important": false
      }, {
         "id": "TA0006_T1208",
         "name": "Kerberoasting",
         "important": false
      }, {
         "id": "TA0006_T1142",
         "name": "Keychain",
         "important": false
      }, {
         "id": "TA0006_T1171",
         "name": "LLMNR/NBT-NS中毒和中继",
         "important": false
      }, {
         "id": "TA0006_T1040",
         "name": "网络嗅探",
         "important": false
      }, {
         "id": "TA0006_T1174",
         "name": "密码过滤DLL",
         "important": false
      }, {
         "id": "TA0006_T1145",
         "name": "私钥",
         "important": false
      }, {
         "id": "TA0006_T1167",
         "name": "Securityd内存",
         "important": false
      }, {
         "id": "TA0006_T1528",
         "name": "窃取应用程序访问令牌",
         "important": false
      }, {
         "id": "TA0006_T1539",
         "name": "窃取Web会话Cookie",
         "important": false
      }, {
         "id": "TA0006_T1111",
         "name": "双因子认证拦截",
         "important": false
      }]
   }, {
      "name": "发现",
      "items": [{
         "id": "TA0007_T1087",
         "name": "账号发现",
         "important": false
      }, {
         "id": "TA0007_T1010",
         "name": "应用窗口发现",
         "important": false
      }, {
         "id": "TA0007_T1217",
         "name": "浏览器书签发现",
         "important": false
      }, {
         "id": "TA0007_T1538",
         "name": "云服务仪表盘",
         "important": false
      }, {
         "id": "TA0007_T1526",
         "name": "云服务发现",
         "important": false
      }, {
         "id": "TA0007_T1482",
         "name": "域信任发现",
         "important": false
      }, {
         "id": "TA0007_T1083",
         "name": "文件和目录发现",
         "important": false
      }, {
         "id": "TA0007_T1046",
         "name": "网络服务扫描",
         "important": false
      }, {
         "id": "TA0007_T1135",
         "name": "网络共享发现",
         "important": false
      }, {
         "id": "TA0007_T1040",
         "name": "网络嗅探",
         "important": false
      }, {
         "id": "TA0007_T1201",
         "name": "密码策略发现",
         "important": false
      }, {
         "id": "TA0007_T1120",
         "name": "周边设备发现",
         "important": false
      }, {
         "id": "TA0007_T1069",
         "name": "权限组发现",
         "important": false
      }, {
         "id": "TA0007_T1057",
         "name": "进程发现",
         "important": false
      }, {
         "id": "TA0007_T1012",
         "name": "查询注册表",
         "important": false
      }, {
         "id": "TA0007_T1018",
         "name": "远程系统发现",
         "important": false
      }, {
         "id": "TA0007_T1063",
         "name": "安全软件发现",
         "important": false
      }, {
         "id": "TA0007_T1518",
         "name": "软件发现",
         "important": false
      }, {
         "id": "TA0007_T1082",
         "name": "系统信息发现",
         "important": false
      }, {
         "id": "TA0007_T1016",
         "name": "系统网络配置发现",
         "important": false
      }, {
         "id": "TA0007_T1049",
         "name": "系统网络连接发现",
         "important": false
      }, {
         "id": "TA0007_T1033",
         "name": "系统所有者/用户发现",
         "important": false
      }, {
         "id": "TA0007_T1007",
         "name": "系统服务发现",
         "important": false
      }, {
         "id": "TA0007_T1124",
         "name": "系统时间发现",
         "important": false
      }, {
         "id": "TA0007_T1497",
         "name": "虚拟化/沙箱逃逸",
         "important": false
      }]
   }, {
      "name": "横向移动",
      "items": [{
         "id": "TA0008_T1155",
         "name": "AppScript",
         "important": false
      }, {
         "id": "TA0008_T1527",
         "name": "应用程序访问令牌",
         "important": false
      }, {
         "id": "TA0008_T1017",
         "name": "应用部署软件",
         "important": false
      }, {
         "id": "TA0008_T1175",
         "name": "COM和分布式COM",
         "important": false
      }, {
         "id": "TA0008_T1210",
         "name": "远程服务利用",
         "important": false
      }, {
         "id": "TA0008_T1534",
         "name": "内部鱼叉式钓鱼攻击",
         "important": false
      }, {
         "id": "TA0008_T1037",
         "name": "登录脚本",
         "important": false
      }, {
         "id": "TA0008_T1075",
         "name": "哈希传递",
         "important": false
      }, {
         "id": "TA0008_T1097",
         "name": "票据传递",
         "important": false
      }, {
         "id": "TA0008_T1076",
         "name": "远程桌面协议",
         "important": false
      }, {
         "id": "TA0008_T1105",
         "name": "远程文件复制",
         "important": false
      }, {
         "id": "TA0008_T1021",
         "name": "远程服务",
         "important": false
      }, {
         "id": "TA0008_T1091",
         "name": "通过移动存储进行复制",
         "important": false
      }, {
         "id": "TA0008_T1051",
         "name": "共享Webroot",
         "important": false
      }, {
         "id": "TA0008_T1184",
         "name": "SSH劫持",
         "important": false
      }, {
         "id": "TA0008_T1080",
         "name": "共享内容污点",
         "important": false
      }, {
         "id": "TA0008_T1072",
         "name": "第三方软件",
         "important": false
      }, {
         "id": "TA0008_T1506",
         "name": "Web会话Cookie",
         "important": false
      }, {
         "id": "TA0008_T1077",
         "name": "Windows管理员共享",
         "important": false
      }, {
         "id": "TA0008_T1028",
         "name": "Windows远程管理",
         "important": false
      }]
   }, {
      "name": "采集",
      "items": [{
         "id": "TA0009_T1123",
         "name": "音频捕捉",
         "important": false
      }, {
         "id": "TA0009_T1119",
         "name": "自动化收集",
         "important": false
      }, {
         "id": "TA0009_T1115",
         "name": "剪贴板数据",
         "important": false
      }, {
         "id": "TA0009_T1530",
         "name": "云存储对象数据",
         "important": false
      }, {
         "id": "TA0009_T1213",
         "name": "信息库数据",
         "important": false
      }, {
         "id": "TA0009_T1005",
         "name": "本地系统数据",
         "important": false
      }, {
         "id": "TA0009_T1039",
         "name": "共享网络驱动器数据",
         "important": false
      }, {
         "id": "TA0009_T1025",
         "name": "可移动媒体数据",
         "important": false
      }, {
         "id": "TA0009_T1074",
         "name": "数据暂存",
         "important": false
      }, {
         "id": "TA0009_T1114",
         "name": "邮件收集",
         "important": false
      }, {
         "id": "TA0009_T1056",
         "name": "输入捕捉",
         "important": false
      }, {
         "id": "TA0009_T1185",
         "name": "MitB",
         "important": false
      }, {
         "id": "TA0009_T1113",
         "name": "屏幕截图",
         "important": false
      }, {
         "id": "TA0009_T1125",
         "name": "视频采集",
         "important": false
      }]
   }, {
      "name": "命令与控制",
      "items": [{
         "id": "TA0011_T1043",
         "name": "通用端口",
         "important": false
      }, {
         "id": "TA0011_T1092",
         "name": "经由可移动媒体通信",
         "important": false
      }, {
         "id": "TA0011_T1090",
         "name": "连接代理",
         "important": false
      }, {
         "id": "TA0011_T1094",
         "name": "自定义C&C协议",
         "important": false
      }, {
         "id": "TA0011_T1024",
         "name": "自定义加密协议",
         "important": false
      }, {
         "id": "TA0011_T1132",
         "name": "数据编码",
         "important": false
      }, {
         "id": "TA0011_T1001",
         "name": "数据混淆",
         "important": false
      }, {
         "id": "TA0011_T1172",
         "name": "域名前置",
         "important": false
      }, {
         "id": "TA0011_T1483",
         "name": "域名生成算法",
         "important": false
      }, {
         "id": "TA0011_T1008",
         "name": "失败回退通道",
         "important": false
      }, {
         "id": "TA0011_T1188",
         "name": "多跳代理",
         "important": false
      }, {
         "id": "TA0011_T1104",
         "name": "多段信道",
         "important": false
      }, {
         "id": "TA0011_T1026",
         "name": "多频段通信",
         "important": false
      }, {
         "id": "TA0011_T1079",
         "name": "多层加密",
         "important": false
      }, {
         "id": "TA0011_T1205",
         "name": "端口试探",
         "important": false
      }, {
         "id": "TA0011_T1219",
         "name": "远程访问工具",
         "important": false
      }, {
         "id": "TA0011_T1105",
         "name": "远程文件复制",
         "important": false
      }, {
         "id": "TA0011_T1071",
         "name": "标准应用层协议",
         "important": false
      }, {
         "id": "TA0011_T1032",
         "name": "标准加密协议",
         "important": false
      }, {
         "id": "TA0011_T1095",
         "name": "标准非应用层协议",
         "important": false
      }, {
         "id": "TA0011_T1065",
         "name": "不常用的端口",
         "important": false
      }, {
         "id": "TA0011_T1102",
         "name": "Web服务",
         "important": false
      }]
   }, {
      "name": "数据渗漏",
      "items": [{
         "id": "TA0010_T1020",
         "name": "自动化数据渗漏",
         "important": false
      }, {
         "id": "TA0010_T1002",
         "name": "数据压缩",
         "important": false
      }, {
         "id": "TA0010_T1022",
         "name": "数据加密",
         "important": false
      }, {
         "id": "TA0010_T1030",
         "name": "数据传输大小限制",
         "important": false
      }, {
         "id": "TA0010_T1048",
         "name": "备用协议上的数据渗漏",
         "important": false
      }, {
         "id": "TA0010_T1041",
         "name": "C&C通道的数据渗漏",
         "important": false
      }, {
         "id": "TA0010_T1011",
         "name": "非C&C通道的数据渗漏",
         "important": false
      }, {
         "id": "TA0010_T1052",
         "name": "物理介质上的数据渗漏",
         "important": false
      }, {
         "id": "TA0010_T1029",
         "name": "定时传输",
         "important": false
      }, {
         "id": "TA0010_T1537",
         "name": "将数据传输到云账户",
         "important": false
      }]
   }, {
      "name": "恶劣影响",
      "items": [{
         "id": "TA0040_T1531",
         "name": "账户访问移除",
         "important": false
      }, {
         "id": "TA0040_T1485",
         "name": "数据破坏",
         "important": false
      }, {
         "id": "TA0040_T1486",
         "name": "为了恶劣影响而数据加密",
         "important": false
      }, {
         "id": "TA0040_T1491",
         "name": "网页置换攻击",
         "important": false
      }, {
         "id": "TA0040_T1488",
         "name": "磁盘内容擦除",
         "important": false
      }, {
         "id": "TA0040_T1487",
         "name": "磁盘结构擦除",
         "important": false
      }, {
         "id": "TA0040_T1499",
         "name": "终端拒绝服务",
         "important": false
      }, {
         "id": "TA0040_T1495",
         "name": "固件损坏",
         "important": false
      }, {
         "id": "TA0040_T1490",
         "name": "禁止系统恢复",
         "important": false
      }, {
         "id": "TA0040_T1498",
         "name": "网络拒绝服务",
         "important": false
      }, {
         "id": "TA0040_T1496",
         "name": "资源劫持",
         "important": false
      }, {
         "id": "TA0040_T1494",
         "name": "运行时数据操控",
         "important": false
      }, {
         "id": "TA0040_T1489",
         "name": "服务停止",
         "important": false
      }, {
         "id": "TA0040_T1492",
         "name": "存储数据操纵",
         "important": false
      }, {
         "id": "TA0040_T1529",
         "name": "系统关闭/重启",
         "important": false
      }, {
         "id": "TA0040_T1493",
         "name": "传输数据操纵",
         "important": false
      }]
   }]
}